{
	"domain": "Tywydd",
	"intents": [
			{
				"name": "WeatherIntent",
				"entities": [				
						{ 
							"name":"Keyword",
							"requirement":"require",
							"keywords": [
								{"keyword":"tywydd"}
							]
						},
						{ 
							"name":"Location",
							"requirement":"optional",
							"keywords": [
								{"keyword":"Aberaeron"},
								{"keyword":"Abertawe"},
								{"keyword":"Aberteifi"},
								{"keyword":"Abertyleri"},
								{"keyword":"Aberystwyth"},
								{"keyword":"Bangor"},
								{"keyword":"Caerdydd"},
								{"keyword":"Caerfyrddin"},
								{"keyword":"Casnewydd"},
								{"keyword":"Castell Nedd"},
								{"keyword":"Dinbych"},
								{"keyword":"Garndolbenmaen"},
								{"keyword":"Hwlffordd"},
								{"keyword":"Llandudno"},
								{"keyword":"Llangefni"},
								{"keyword":"Merthyr Tudful"},
								{"keyword":"Pen-y-bont ar Ogwr"},
								{"keyword":"Pontypridd"},
								{"keyword":"Pwllheli"},
								{"keyword":"Y Barri"},
								{"keyword":"Y Trallwng"},
								{"keyword":"Yr Wyddgrug"}
							]
						}
						
				]
			}
	]
}
